{"hei":"ho","objects":["{\n    \"type\": \"StaticPicture\",\n    \"position\": {\n        \"x\": -36.4,\n        \"y\": 47.91,\n        \"width\": 100,\n        \"height\": 100\n    },\n    \"imagePath\": \"https://i.imgur.com/w9dZE0H.png\"\n}","{\n    \"type\": \"StaticPicture\",\n    \"position\": {\n        \"x\": 99.94,\n        \"y\": -89.44,\n        \"width\": 100,\n        \"height\": 100\n    },\n    \"imagePath\": \"https://i.imgur.com/w9dZE0H.png\"\n}","{\n    \"type\": \"StaticPicture\",\n    \"position\": {\n        \"x\": -350,\n        \"y\": -77.32,\n        \"width\": 100,\n        \"height\": 100\n    },\n    \"imagePath\": \"https://i.imgur.com/w9dZE0H.png\"\n}","{\n    \"type\": \"StaticPicture\",\n    \"position\": {\n        \"x\": -182,\n        \"y\": -220.5,\n        \"width\": 100,\n        \"height\": 100\n    },\n    \"imagePath\": \"https://i.imgur.com/w9dZE0H.png\"\n}","{\n    \"type\": \"StaticPicture\",\n    \"position\": {\n        \"x\": 69.64,\n        \"y\": -219.5,\n        \"width\": 100,\n        \"height\": 100\n    },\n    \"imagePath\": \"https://i.imgur.com/w9dZE0H.png\"\n}","{\n    \"type\": \"StaticPicture\",\n    \"position\": {\n        \"x\": 251,\n        \"y\": 41.86,\n        \"width\": 100,\n        \"height\": 100\n    },\n    \"imagePath\": \"https://i.imgur.com/w9dZE0H.png\"\n}","{\n    \"type\": \"StaticPicture\",\n    \"position\": {\n        \"x\": 114,\n        \"y\": 249.5,\n        \"width\": 100,\n        \"height\": 100\n    },\n    \"imagePath\": \"https://i.imgur.com/w9dZE0H.png\"\n}","{\n    \"type\": \"StaticPicture\",\n    \"position\": {\n        \"x\": 374,\n        \"y\": 195.5,\n        \"width\": 100,\n        \"height\": 100\n    },\n    \"imagePath\": \"https://i.imgur.com/w9dZE0H.png\"\n}","{\n    \"type\": \"StaticPicture\",\n    \"position\": {\n        \"x\": -479,\n        \"y\": -255.5,\n        \"width\": 100,\n        \"height\": 100\n    },\n    \"imagePath\": \"/static/assets/art/bar.jpg\"\n}","{\n    \"type\": \"StaticPicture\",\n    \"position\": {\n        \"x\": -258,\n        \"y\": -347.5,\n        \"width\": 100,\n        \"height\": 100\n    },\n    \"imagePath\": \"/static/assets/art/bar.jpg\"\n}","{\n    \"type\": \"StaticPicture\",\n    \"position\": {\n        \"x\": 54.49,\n        \"y\": -287.5,\n        \"width\": 100,\n        \"height\": 100\n    },\n    \"imagePath\": \"/static/assets/art/bar.jpg\"\n}","{\n    \"type\": \"StaticPicture\",\n    \"position\": {\n        \"x\": 205,\n        \"y\": -324.5,\n        \"width\": 100,\n        \"height\": 100\n    },\n    \"imagePath\": \"/static/assets/art/bar.jpg\"\n}","{\n    \"type\": \"StaticPicture\",\n    \"position\": {\n        \"x\": -186,\n        \"y\": -96.5,\n        \"width\": 100,\n        \"height\": 100\n    },\n    \"imagePath\": \"/static/assets/art/bar.jpg\"\n}","{\n    \"type\": \"StaticPicture\",\n    \"position\": {\n        \"x\": -14.190000000000001,\n        \"y\": -70.25,\n        \"width\": 100,\n        \"height\": 100\n    },\n    \"imagePath\": \"/static/assets/art/bar.jpg\"\n}","{\n    \"type\": \"StaticPicture\",\n    \"position\": {\n        \"x\": -175.39,\n        \"y\": -169.39,\n        \"width\": 100,\n        \"height\": 100\n    },\n    \"imagePath\": \"/static/assets/art/bar.jpg\"\n}","{\n    \"type\": \"StaticPicture\",\n    \"position\": {\n        \"x\": 10.05,\n        \"y\": -152.5,\n        \"width\": 100,\n        \"height\": 100\n    },\n    \"imagePath\": \"/static/assets/art/bar.jpg\"\n}","{\n    \"type\": \"StaticPicture\",\n    \"position\": {\n        \"x\": 1.9699999999999998,\n        \"y\": -52.07,\n        \"width\": 100,\n        \"height\": 100\n    },\n    \"imagePath\": \"/static/assets/art/bar.jpg\"\n}","{\n    \"type\": \"StaticPicture\",\n    \"position\": {\n        \"x\": -93.99,\n        \"y\": 99.44,\n        \"width\": 100,\n        \"height\": 100\n    },\n    \"imagePath\": \"/static/assets/art/bar.jpg\"\n}","{\n    \"type\": \"StaticPicture\",\n    \"position\": {\n        \"x\": 216,\n        \"y\": 108.5,\n        \"width\": 100,\n        \"height\": 100\n    },\n    \"imagePath\": \"/static/assets/art/bar.jpg\"\n}","{\n    \"type\": \"StaticPicture\",\n    \"position\": {\n        \"x\": 301,\n        \"y\": 191.5,\n        \"width\": 100,\n        \"height\": 100\n    },\n    \"imagePath\": \"/static/assets/art/bar.jpg\"\n}","{\n    \"type\": \"StaticPicture\",\n    \"position\": {\n        \"x\": 399,\n        \"y\": 232.5,\n        \"width\": 100,\n        \"height\": 100\n    },\n    \"imagePath\": \"/static/assets/art/bar.jpg\"\n}","{\n    \"type\": \"StaticPicture\",\n    \"position\": {\n        \"x\": 92.95,\n        \"y\": 161.45,\n        \"width\": 100,\n        \"height\": 100\n    },\n    \"imagePath\": \"/static/assets/art/bar.jpg\"\n}","{\n    \"type\": \"StaticPicture\",\n    \"position\": {\n        \"x\": 320,\n        \"y\": 287.5,\n        \"width\": 100,\n        \"height\": 100\n    },\n    \"imagePath\": \"/static/assets/art/bar.jpg\"\n}","{\n    \"type\": \"StaticPicture\",\n    \"position\": {\n        \"x\": 433,\n        \"y\": 309.5,\n        \"width\": 100,\n        \"height\": 100\n    },\n    \"imagePath\": \"/static/assets/art/bar.jpg\"\n}","{\n    \"type\": \"StaticPicture\",\n    \"position\": {\n        \"x\": 277.95,\n        \"y\": 268.45,\n        \"width\": 100,\n        \"height\": 100\n    },\n    \"imagePath\": \"/static/assets/art/bar.jpg\"\n}","{\n    \"type\": \"StaticPicture\",\n    \"position\": {\n        \"x\": 344,\n        \"y\": 182.5,\n        \"width\": 100,\n        \"height\": 100\n    },\n    \"imagePath\": \"/static/assets/art/bar.jpg\"\n}","{\n    \"type\": \"StaticPicture\",\n    \"position\": {\n        \"x\": -56.61,\n        \"y\": -144.5,\n        \"width\": 100,\n        \"height\": 100\n    },\n    \"imagePath\": \"/static/assets/art/cute.jpg\"\n}","{\n    \"type\": \"StaticPicture\",\n    \"position\": {\n        \"x\": 75.7,\n        \"y\": 25.7,\n        \"width\": 100,\n        \"height\": 100\n    },\n    \"imagePath\": \"/static/assets/art/cute.jpg\"\n}","{\n    \"type\": \"StaticPicture\",\n    \"position\": {\n        \"x\": 431,\n        \"y\": 399.5,\n        \"width\": 100,\n        \"height\": 100\n    },\n    \"imagePath\": \"/static/assets/art/cute.jpg\"\n}","{\n    \"type\": \"StaticPicture\",\n    \"position\": {\n        \"x\": 248,\n        \"y\": 323.5,\n        \"width\": 100,\n        \"height\": 100\n    },\n    \"imagePath\": \"/static/assets/art/girl.jpg\"\n}","{\n    \"type\": \"StaticPicture\",\n    \"position\": {\n        \"x\": 350,\n        \"y\": 348.5,\n        \"width\": 100,\n        \"height\": 100\n    },\n    \"imagePath\": \"/static/assets/art/girl.jpg\"\n}","{\n    \"type\": \"StaticPicture\",\n    \"position\": {\n        \"x\": 415,\n        \"y\": 438.5,\n        \"width\": 100,\n        \"height\": 100\n    },\n    \"imagePath\": \"/static/assets/art/girl.jpg\"\n}","{\n    \"type\": \"StaticPicture\",\n    \"position\": {\n        \"x\": 408,\n        \"y\": 425.5,\n        \"width\": 100,\n        \"height\": 100\n    },\n    \"imagePath\": \"/static/assets/art/sexy.jpg\"\n}","{\n    \"type\": \"StaticPicture\",\n    \"position\": {\n        \"x\": 424,\n        \"y\": 429.5,\n        \"width\": 100,\n        \"height\": 100\n    },\n    \"imagePath\": \"/static/assets/art/strip.jpg\"\n}","{\n    \"type\": \"StaticPicture\",\n    \"position\": {\n        \"x\": 316,\n        \"y\": -290.5,\n        \"width\": 100,\n        \"height\": 100\n    },\n    \"imagePath\": \"/static/assets/art/strip.jpg\"\n}","{\n    \"type\": \"StaticPicture\",\n    \"position\": {\n        \"x\": 321,\n        \"y\": 108.5,\n        \"width\": 100,\n        \"height\": 100\n    },\n    \"imagePath\": \"/static/assets/art/strip.jpg\"\n}","{\n    \"type\": \"StaticPicture\",\n    \"position\": {\n        \"x\": 401,\n        \"y\": 377.5,\n        \"width\": 100,\n        \"height\": 100\n    },\n    \"imagePath\": \"/static/assets/art/strip.jpg\"\n}","{\n    \"type\": \"StaticPicture\",\n    \"position\": {\n        \"x\": 440,\n        \"y\": 416.5,\n        \"width\": 100,\n        \"height\": 100\n    },\n    \"imagePath\": \"/static/assets/art/bar.jpg\"\n}","{\n    \"type\": \"StaticPicture\",\n    \"position\": {\n        \"x\": -886.7628152673307,\n        \"y\": -113.53120479221725,\n        \"width\": 100,\n        \"height\": 100\n    },\n    \"imagePath\": \"/static/assets/art/bar.jpg\"\n}","{\n    \"type\": \"StaticPicture\",\n    \"position\": {\n        \"x\": -16.816099929404558,\n        \"y\": -4.090041637251897,\n        \"width\": 100,\n        \"height\": 100\n    },\n    \"imagePath\": \"/static/assets/art/bar.jpg\"\n}","{\n    \"type\": \"StaticPicture\",\n    \"position\": {\n        \"x\": 17.284452835723958,\n        \"y\": 194.70401895372137,\n        \"width\": 100,\n        \"height\": 100\n    },\n    \"imagePath\": \"/static/assets/art/bar.jpg\"\n}","{\n    \"type\": \"StaticPicture\",\n    \"position\": {\n        \"x\": 465.16262347686865,\n        \"y\": 557.2019781828176,\n        \"width\": 100,\n        \"height\": 100\n    },\n    \"imagePath\": \"/static/assets/art/bar.jpg\"\n}","{\n    \"type\": \"StaticPicture\",\n    \"position\": {\n        \"x\": 505.51822634776073,\n        \"y\": -152.66708008179768,\n        \"width\": 100,\n        \"height\": 100\n    },\n    \"imagePath\": \"/static/assets/art/bar.jpg\"\n}","{\n    \"type\": \"StaticPicture\",\n    \"position\": {\n        \"x\": 114.82389546487724,\n        \"y\": -1838.1372403254336,\n        \"width\": 100,\n        \"height\": 100\n    },\n    \"imagePath\": \"/static/assets/art/bar.jpg\"\n}","{\n    \"type\": \"StaticPicture\",\n    \"position\": {\n        \"x\": 205,\n        \"y\": 297.5,\n        \"width\": 100,\n        \"height\": 100\n    },\n    \"imagePath\": \"/static/assets/art/bar.jpg\"\n}"]}