{"hei":"ho","objects":["{\n    \"type\": \"StaticPicture\",\n    \"position\": {\n        \"x\": -122,\n        \"y\": 324.5,\n        \"width\": 1,\n        \"height\": 1\n    },\n    \"imagePath\": \"static/assets/image/Chicken_Sprite_Sheet_Light_Brown.png\"\n}","{\n    \"type\": \"StaticPicture\",\n    \"position\": {\n        \"x\": -134,\n        \"y\": 57.019999999999996,\n        \"width\": 1,\n        \"height\": 1\n    },\n    \"imagePath\": \"static/assets/image/Chicken_Sprite_Sheet_Light_Brown.png\"\n}","{\n    \"type\": \"StaticPicture\",\n    \"position\": {\n        \"x\": 44.39,\n        \"y\": 35.8,\n        \"width\": 1,\n        \"height\": 1\n    },\n    \"imagePath\": \"static/assets/image/Chicken_Sprite_Sheet_Light_Brown.png\"\n}","{\n    \"type\": \"StaticPicture\",\n    \"position\": {\n        \"x\": 399,\n        \"y\": 359.5,\n        \"width\": 100,\n        \"height\": 100\n    },\n    \"imagePath\": \"static/assets/fire_and_sparks/Fire+Sparks2.png\"\n}","{\n    \"type\": \"StaticPicture\",\n    \"position\": {\n        \"x\": 115,\n        \"y\": 26.71,\n        \"width\": 100,\n        \"height\": 100\n    },\n    \"imagePath\": \"static/assets/fire_and_sparks/Fire+Sparks2.png\"\n}","{\n    \"type\": \"StaticPicture\",\n    \"position\": {\n        \"x\": -19.240000000000002,\n        \"y\": -42.97,\n        \"width\": 100,\n        \"height\": 100\n    },\n    \"imagePath\": \"static/assets/fire_and_sparks/Fire+Sparks2.png\"\n}","{\n    \"type\": \"StaticPicture\",\n    \"position\": {\n        \"x\": -234,\n        \"y\": -126.5,\n        \"width\": 100,\n        \"height\": 100\n    },\n    \"imagePath\": \"static/assets/fire_and_sparks/Fire+Sparks2.png\"\n}","{\n    \"type\": \"Chicken\",\n    \"position\": {\n        \"x\": 96.91,\n        \"y\": -168.5,\n        \"width\": 60,\n        \"height\": 60\n    },\n    \"objectId\": \"421805e5-2ee8-45aa-bdf0-3297a8f62cc1\"\n}","{\n    \"type\": \"Chicken\",\n    \"position\": {\n        \"x\": -62,\n        \"y\": -74,\n        \"width\": 60,\n        \"height\": 60\n    },\n    \"objectId\": \"05ef67f9-dc24-4d28-8f38-111a4caeaf1a\"\n}","{\n    \"type\": \"Chicken\",\n    \"position\": {\n        \"x\": 164,\n        \"y\": -44.99,\n        \"width\": 60,\n        \"height\": 60\n    },\n    \"objectId\": \"58271ca2-6727-429a-bd2d-7768f3fbc5c3\"\n}","{\n    \"type\": \"Chicken\",\n    \"position\": {\n        \"x\": -112,\n        \"y\": -206.5,\n        \"width\": 60,\n        \"height\": 60\n    },\n    \"objectId\": \"334f1c2b-d018-4dde-a630-220d586667aa\"\n}","{\n    \"type\": \"Chicken\",\n    \"position\": {\n        \"x\": -342,\n        \"y\": -85,\n        \"width\": 60,\n        \"height\": 60\n    },\n    \"objectId\": \"5a16b84d-9f2c-4022-876a-ad2f862ef315\"\n}","{\n    \"type\": \"StaticPicture\",\n    \"position\": {\n        \"x\": 23.18,\n        \"y\": 329.5,\n        \"width\": 100,\n        \"height\": 100\n    },\n    \"imagePath\": \"static/assets/floors/wooden_floor_128x128.png\"\n}","{\n    \"type\": \"Chicken\",\n    \"position\": {\n        \"x\": 13,\n        \"y\": 311,\n        \"width\": 60,\n        \"height\": 60\n    },\n    \"objectId\": \"96533d0e-580a-4fbc-bc09-b0be5a439924\"\n}","{\n    \"type\": \"StaticPicture\",\n    \"position\": {\n        \"x\": -235,\n        \"y\": 93.38,\n        \"width\": 100,\n        \"height\": 100\n    },\n    \"imagePath\": \"static/assets/floors/wooden_floor_128x128.png\"\n}","{\n    \"type\": \"StaticPicture\",\n    \"position\": {\n        \"x\": -499,\n        \"y\": -165.5,\n        \"width\": 100,\n        \"height\": 100\n    },\n    \"imagePath\": \"static/assets/floors/wooden_floor_128x128.png\"\n}","{\n    \"type\": \"StaticPicture\",\n    \"position\": {\n        \"x\": -408,\n        \"y\": -194.5,\n        \"width\": 100,\n        \"height\": 100\n    },\n    \"imagePath\": \"static/assets/floors/wooden_floor_128x128.png\"\n}","{\n    \"type\": \"StaticPicture\",\n    \"position\": {\n        \"x\": -392,\n        \"y\": -98.5,\n        \"width\": 100,\n        \"height\": 100\n    },\n    \"imagePath\": \"static/assets/floors/wooden_floor_128x128.png\"\n}","{\n    \"type\": \"StaticPicture\",\n    \"position\": {\n        \"x\": -464,\n        \"y\": -180.5,\n        \"width\": 100,\n        \"height\": 100\n    },\n    \"imagePath\": \"static/assets/floors/wooden_floor_128x128.png\"\n}","{\n    \"type\": \"StaticPicture\",\n    \"position\": {\n        \"x\": -449,\n        \"y\": -57.12,\n        \"width\": 100,\n        \"height\": 100\n    },\n    \"imagePath\": \"static/assets/floors/wooden_floor_128x128.png\"\n}","{\n    \"type\": \"StaticPicture\",\n    \"position\": {\n        \"x\": -482,\n        \"y\": -120.5,\n        \"width\": 100,\n        \"height\": 100\n    },\n    \"imagePath\": \"static/assets/floors/wooden_floor_128x128.png\"\n}","{\n    \"type\": \"StaticPicture\",\n    \"position\": {\n        \"x\": -482,\n        \"y\": -120.5,\n        \"width\": 100,\n        \"height\": 100\n    },\n    \"imagePath\": \"static/assets/floors/wooden_floor_128x128.png\"\n}","{\n    \"type\": \"StaticPicture\",\n    \"position\": {\n        \"x\": -482,\n        \"y\": -120.5,\n        \"width\": 100,\n        \"height\": 100\n    },\n    \"imagePath\": \"static/assets/floors/wooden_floor_128x128.png\"\n}","{\n    \"type\": \"StaticPicture\",\n    \"position\": {\n        \"x\": -482,\n        \"y\": -120.5,\n        \"width\": 100,\n        \"height\": 100\n    },\n    \"imagePath\": \"static/assets/floors/wooden_floor_128x128.png\"\n}","{\n    \"type\": \"StaticPicture\",\n    \"position\": {\n        \"x\": -482,\n        \"y\": -120.5,\n        \"width\": 100,\n        \"height\": 100\n    },\n    \"imagePath\": \"static/assets/floors/wooden_floor_128x128.png\"\n}","{\n    \"type\": \"StaticPicture\",\n    \"position\": {\n        \"x\": -482,\n        \"y\": -120.5,\n        \"width\": 100,\n        \"height\": 100\n    },\n    \"imagePath\": \"static/assets/floors/wooden_floor_128x128.png\"\n}","{\n    \"type\": \"StaticPicture\",\n    \"position\": {\n        \"x\": -482,\n        \"y\": -120.5,\n        \"width\": 100,\n        \"height\": 100\n    },\n    \"imagePath\": \"static/assets/floors/wooden_floor_128x128.png\"\n}","{\n    \"type\": \"StaticPicture\",\n    \"position\": {\n        \"x\": -482,\n        \"y\": -120.5,\n        \"width\": 100,\n        \"height\": 100\n    },\n    \"imagePath\": \"static/assets/floors/wooden_floor_128x128.png\"\n}","{\n    \"type\": \"StaticPicture\",\n    \"position\": {\n        \"x\": -482,\n        \"y\": -120.5,\n        \"width\": 100,\n        \"height\": 100\n    },\n    \"imagePath\": \"static/assets/floors/wooden_floor_128x128.png\"\n}","{\n    \"type\": \"StaticPicture\",\n    \"position\": {\n        \"x\": -125,\n        \"y\": -204.5,\n        \"width\": 100,\n        \"height\": 100\n    },\n    \"imagePath\": \"static/assets/floors/wooden_floor_128x128.png\"\n}","{\n    \"type\": \"StaticPicture\",\n    \"position\": {\n        \"x\": -125,\n        \"y\": -204.5,\n        \"width\": 100,\n        \"height\": 100\n    },\n    \"imagePath\": \"static/assets/floors/wooden_floor_128x128.png\"\n}","{\n    \"type\": \"StaticPicture\",\n    \"position\": {\n        \"x\": 25.2,\n        \"y\": -260.5,\n        \"width\": 100,\n        \"height\": 100\n    },\n    \"imagePath\": \"static/assets/floors/wooden_floor_128x128.png\"\n}","{\n    \"type\": \"StaticPicture\",\n    \"position\": {\n        \"x\": 25.2,\n        \"y\": -260.5,\n        \"width\": 100,\n        \"height\": 100\n    },\n    \"imagePath\": \"static/assets/floors/wooden_floor_128x128.png\"\n}","{\n    \"type\": \"StaticPicture\",\n    \"position\": {\n        \"x\": 25.2,\n        \"y\": -260.5,\n        \"width\": 100,\n        \"height\": 100\n    },\n    \"imagePath\": \"static/assets/floors/wooden_floor_128x128.png\"\n}","{\n    \"type\": \"StaticPicture\",\n    \"position\": {\n        \"x\": 25.2,\n        \"y\": -260.5,\n        \"width\": 100,\n        \"height\": 100\n    },\n    \"imagePath\": \"static/assets/floors/wooden_floor_128x128.png\"\n}","{\n    \"type\": \"StaticPicture\",\n    \"position\": {\n        \"x\": 71.66,\n        \"y\": -183.5,\n        \"width\": 100,\n        \"height\": 100\n    },\n    \"imagePath\": \"static/assets/floors/wooden_floor_128x128.png\"\n}","{\n    \"type\": \"StaticPicture\",\n    \"position\": {\n        \"x\": 71.66,\n        \"y\": -183.5,\n        \"width\": 100,\n        \"height\": 100\n    },\n    \"imagePath\": \"static/assets/floors/wooden_floor_128x128.png\"\n}","{\n    \"type\": \"Chicken\",\n    \"position\": {\n        \"x\": 66,\n        \"y\": -223,\n        \"width\": 60,\n        \"height\": 60\n    },\n    \"objectId\": \"25554aa8-ff4a-4226-8006-8246658002e3\"\n}","{\n    \"type\": \"Chicken\",\n    \"objectId\": \"d33e7f38-d5be-4443-8abc-544dc2479576\",\n    \"position\": {\n        \"x\": 423,\n        \"y\": -2,\n        \"width\": 60,\n        \"height\": 60\n    }\n}","{\n    \"type\": \"Chicken\",\n    \"objectId\": \"fcd35520-342a-4ac4-a7a9-58b2d03438e4\",\n    \"position\": {\n        \"x\": 418,\n        \"y\": -110,\n        \"width\": 60,\n        \"height\": 60\n    }\n}","{\n    \"type\": \"Chicken\",\n    \"objectId\": \"598c470d-c94c-4b95-aeef-1c5f5e3afcb6\",\n    \"position\": {\n        \"x\": 420,\n        \"y\": -235,\n        \"width\": 60,\n        \"height\": 60\n    }\n}"]}